CHANGES
CHANGES.txt
CONTRIBUTORS.txt
README.txt
bootstrap.py
buildout.cfg
setup.cfg
setup.py
iw/__init__.py
iw.recipe.pound.egg-info/PKG-INFO
iw.recipe.pound.egg-info/SOURCES.txt
iw.recipe.pound.egg-info/dependency_links.txt
iw.recipe.pound.egg-info/entry_points.txt
iw.recipe.pound.egg-info/namespace_packages.txt
iw.recipe.pound.egg-info/not-zip-safe
iw.recipe.pound.egg-info/requires.txt
iw.recipe.pound.egg-info/top_level.txt
iw/recipe/__init__.py
iw/recipe/pound/README.txt
iw/recipe/pound/__init__.py
iw/recipe/pound/build.py
iw/recipe/pound/config.py
iw/recipe/pound/pound.cfg.tpl
iw/recipe/pound/pound_backend.cfg_tmpl
iw/recipe/pound/pound_balancer.cfg_tmpl
iw/recipe/pound/poundctl.tpl
iw/recipe/pound/docs/building.txt
iw/recipe/pound/docs/configuring.txt
iw/recipe/pound/docs/technical.txt
iw/recipe/pound/doctests/README.txt
iw/recipe/pound/tests/Pound-2.3.2.tgz
iw/recipe/pound/tests/__init__.py
iw/recipe/pound/tests/test_pounddocs.py