Metadata-Version: 1.0
Name: iw.recipe.pound
Version: 0.4.1
Summary: Recipe to install and configure Pound
Home-page: http://plone.org/products/iw-recipes
Author: Ingeniweb
Author-email: support@ingeniweb.com
License: GPL
Keywords: pound zope plone recipe
Platform: UNKNOWN
Classifier: Programming Language :: Python
Classifier: Topic :: Software Development :: Libraries :: Python Modules
